LICENSE
MANIFEST.in
README.md
requirements.txt
setup.py
quantiphyse_asl.egg-info/PKG-INFO
quantiphyse_asl.egg-info/SOURCES.txt
quantiphyse_asl.egg-info/dependency_links.txt
quantiphyse_asl.egg-info/entry_points.txt
quantiphyse_asl.egg-info/requires.txt
quantiphyse_asl.egg-info/top_level.txt
quantiphyse_basil/__init__.py
quantiphyse_basil/_version.py
quantiphyse_basil/asl.png
quantiphyse_basil/asl.svg
quantiphyse_basil/asl_testdata.nii.gz
quantiphyse_basil/aslimage_widget.py
quantiphyse_basil/mp_testdata.nii.gz
quantiphyse_basil/multiphase_template.py
quantiphyse_basil/oxasl_process.py
quantiphyse_basil/oxasl_widgets.py
quantiphyse_basil/process.py
quantiphyse_basil/tests.py
quantiphyse_basil/veasl_widgets.py
quantiphyse_basil/widgets.py